yamc/__init__.py
yamc/yamc.cpython-313-x86_64-linux-gnu.so
yamc-0.2.2.dist-info/METADATA
yamc-0.2.2.dist-info/WHEEL
yamc.libs/libcom_err-2abe824b.so.2
yamc.libs/libcrypto-d3570994.so.10
yamc.libs/libgssapi_krb5-497db0c6.so.2
yamc.libs/libk5crypto-b1f99d5c.so.3
yamc.libs/libkeyutils-dfe70bd6.so.1
yamc.libs/libkrb5-fcafa220.so.3
yamc.libs/libkrb5support-d0bcff84.so.0
yamc.libs/libpcre-9513aab5.so.1
yamc.libs/libselinux-0922c95c.so.1
yamc.libs/libssl-cd1d6220.so.10
yamc-0.2.2.dist-info/RECORD
