Metadata-Version: 2.4
Name: yamc
Version: 0.2.2
Summary: Material builder for Monte Carlo simulations
License: MIT
